xfunc/__init__.py
xfunc/__main__.py
xfunc/hello.py
xfunc-2024.12.10.1.dist-info/METADATA
xfunc-2024.12.10.1.dist-info/WHEEL
xfunc-2024.12.10.1.dist-info/top_level.txt
xfunc-2024.12.10.1.dist-info/RECORD
