Metadata-Version: 2.1
Name: xfunc
Version: 2024.12.10.1
Summary: cikuu tools
Home-page: http://www.cikuu.com
Author: cikuu
Author-email: info@cikuu.com
License: MIT Licence
Keywords: pip
Platform: any
Requires-Dist: redis
Requires-Dist: fire
